autopyexec/__init__.py
autopyexec/install_hook.py
autopyexec-0.1.0.dist-info/METADATA
autopyexec-0.1.0.dist-info/WHEEL
autopyexec-0.1.0.dist-info/top_level.txt
autopyexec-0.1.0.dist-info/RECORD
